tkinter_itk/Annotation_manager.py
tkinter_itk/Annotation_point.py
tkinter_itk/DICOM_serie_instance.py
tkinter_itk/DICOM_serie_manager.py
tkinter_itk/ITK_viewer.py
tkinter_itk/ITKsegmentationframe.py
tkinter_itk/ITKviewerframe.py
tkinter_itk/ImagesFrameManager.py
tkinter_itk/Utils.py
tkinter_itk/__init__.py
tkinter_itk/segmentation_serie_manager.py
tkinter_itk/segmentationbaseclass.py
tkinter_itk/threading_tk.py
tkinter_itk/topbar.py
tkinter_itk/menu/__init__.py
tkinter_itk/menu/fileMenu.py
tkinter_itk/menu/helpMenu.py
tkinter_itk/menu/segmentationMenu.py
tkinter_itk/plugins/__init__.py
tkinter_itk/plugins/itk_viewer_plugin_SAM_segmentation.py
tkinter_itk/plugins/itk_viewer_plugin_manual_segmentation.py
tkinter_itk-0.0.1.dist-info/METADATA
tkinter_itk-0.0.1.dist-info/WHEEL
tkinter_itk-0.0.1.dist-info/top_level.txt
tkinter_itk-0.0.1.dist-info/RECORD
